lazyqml/__init__.py
lazyqml/lazyqml.py
lazyqml/Factories/__init__.py
lazyqml/Factories/Circuits/AmplitudeEmbedding.py
lazyqml/Factories/Circuits/HCzRx.py
lazyqml/Factories/Circuits/HardwareEfficient.py
lazyqml/Factories/Circuits/RxEmbedding.py
lazyqml/Factories/Circuits/RyEmbedding.py
lazyqml/Factories/Circuits/RzEmbedding.py
lazyqml/Factories/Circuits/TreeTensor.py
lazyqml/Factories/Circuits/TwoLocal.py
lazyqml/Factories/Circuits/ZzEmbedding.py
lazyqml/Factories/Circuits/fCircuits.py
lazyqml/Factories/Dispatchers/Dispatcher.py
lazyqml/Factories/Models/Hybrid.py
lazyqml/Factories/Models/QNNBag.py
lazyqml/Factories/Models/QNNTorch.py
lazyqml/Factories/Models/QSVM.py
lazyqml/Factories/Models/_QNNPennylane.py
lazyqml/Factories/Models/fModels.py
lazyqml/Factories/Preprocessing/Pca.py
lazyqml/Factories/Preprocessing/Sanitizer.py
lazyqml/Factories/Preprocessing/__init__.py
lazyqml/Factories/Preprocessing/fPreprocessing.py
lazyqml/Global/globalEnums.py
lazyqml/Interfaces/__init__.py
lazyqml/Interfaces/iAnsatz.py
lazyqml/Interfaces/iCircuit.py
lazyqml/Interfaces/iModel.py
lazyqml/Interfaces/iPreprocessing.py
lazyqml/Utils/Utils.py
lazyqml/Utils/Validator.py
lazyqml-3.2.2.dist-info/AUTHORS.rst
lazyqml-3.2.2.dist-info/LICENSE
lazyqml-3.2.2.dist-info/LICENSE copy
lazyqml-3.2.2.dist-info/METADATA
lazyqml-3.2.2.dist-info/WHEEL
lazyqml-3.2.2.dist-info/entry_points.txt
lazyqml-3.2.2.dist-info/top_level.txt
lazyqml-3.2.2.dist-info/RECORD
