Metadata-Version: 2.2
Name: lazyqml
Version: 3.2.2
Summary: LazyQML benchmarking utility to test quantum machine learning models.
Author-email: QHPC Group <qhpcgroup@gmail.com>
License: MIT License
Project-URL: Homepage, https://github.com/QHPC-SP-Research-Lab/LazyQML
Keywords: lazyqml
Classifier: Intended Audience :: Science/Research
Classifier: License :: OSI Approved :: MIT License
Classifier: Natural Language :: English
Classifier: Programming Language :: Python :: 3.10
Requires-Python: >=3.9
License-File: LICENSE
License-File: LICENSE copy
License-File: AUTHORS.rst
Requires-Dist: wheel
Requires-Dist: tabulate
Requires-Dist: torch
Requires-Dist: torchaudio
Requires-Dist: torchvision
Requires-Dist: scipy
Requires-Dist: scikit-learn
Requires-Dist: PennyLane==0.39
Requires-Dist: PennyLane_Lightning==0.39
Requires-Dist: PennyLane_Lightning_GPU==0.39
Requires-Dist: custatevec_cu12
Requires-Dist: ucimlrepo
Requires-Dist: pydantic
Requires-Dist: psutil
Requires-Dist: pandas
Requires-Dist: joblib
Requires-Dist: gputil
Provides-Extra: all
Requires-Dist: lazyqml[extra]; extra == "all"
Provides-Extra: extra
Requires-Dist: pandas; extra == "extra"
